plotly_kz_map/__init__.py
plotly_kz_map/assets/kz-adm1.geojson
plotly_kz_map-0.0.3.dist-info/METADATA
plotly_kz_map-0.0.3.dist-info/WHEEL
plotly_kz_map-0.0.3.dist-info/licenses/LICENSE
plotly_kz_map-0.0.3.dist-info/RECORD
