Metadata-Version: 2.3
Name: plotly-kz-map
Version: 0.0.3
Summary: A Python package that provides a simple interface to create Kazakhstan maps using Plotly
Project-URL: Homepage, https://github.com/aidoskanapyanov/plotly-kz-map
Project-URL: Issues, https://github.com/aidoskanapyanov/plotly-kz-map/issues
Project-URL: Source, https://github.com/aidoskanapyanov/plotly-kz-map
Author-email: Aidos Kanapyanov <aidos.kanapyanov2@gmail.com>
License-File: LICENSE
Classifier: License :: OSI Approved :: MIT License
Classifier: Operating System :: OS Independent
Classifier: Programming Language :: Python :: 3
Requires-Python: >=3.8
Requires-Dist: geopandas>=1.0.0
Requires-Dist: plotly>=5.0.0
